edco/__init__.py
edco/__main__.py
edco/commands.py
edco/data.py
edco/pyrightconfig.json
edco/tui.py
edco/completions/_config
edco/completions/config
edco/completions/config.fish
edco-1.2.dist-info/licenses/LICENSE
edco-1.2.dist-info/METADATA
edco-1.2.dist-info/WHEEL
edco-1.2.dist-info/entry_points.txt
edco-1.2.dist-info/top_level.txt
edco-1.2.dist-info/RECORD
