Metadata-Version: 2.4
Name: edco
Version: 1.2
Summary: EDCO - EDit COnfigs, make your configuration easier
Author-email: Sevaed <seva.romanovsky@gmail.com>
License: MIT
Classifier: Programming Language :: Python :: 3
Classifier: License :: OSI Approved :: MIT License
Classifier: Operating System :: OS Independent
Requires-Python: >=3.8
License-File: LICENSE
Dynamic: license-file
